README.md
setup.cfg
setup.py
ppln/__init__.py
ppln/batch_processor.py
ppln/experiment.py
ppln/factory.py
ppln/hook_list.py
ppln/inference.py
ppln/runner.py
ppln.egg-info/PKG-INFO
ppln.egg-info/SOURCES.txt
ppln.egg-info/dependency_links.txt
ppln.egg-info/requires.txt
ppln.egg-info/top_level.txt
ppln/data/__init__.py
ppln/data/datasets.py
ppln/data/samplers.py
ppln/data/transforms.py
ppln/fileio/__init__.py
ppln/fileio/io.py
ppln/fileio/parse.py
ppln/fileio/handlers/__init__.py
ppln/fileio/handlers/base.py
ppln/fileio/handlers/json_handler.py
ppln/fileio/handlers/pickle_handler.py
ppln/fileio/handlers/yaml_handler.py
ppln/hooks/__init__.py
ppln/hooks/apex.py
ppln/hooks/base.py
ppln/hooks/checkpoint.py
ppln/hooks/dist.py
ppln/hooks/early_stopping.py
ppln/hooks/log_buffer.py
ppln/hooks/lr_scheduler.py
ppln/hooks/optimizer.py
ppln/hooks/priority.py
ppln/hooks/registry.py
ppln/hooks/resume.py
ppln/hooks/sampler.py
ppln/hooks/timer.py
ppln/hooks/logger/__init__.py
ppln/hooks/logger/base.py
ppln/hooks/logger/progress_bar.py
ppln/hooks/logger/text.py
ppln/hooks/logger/utils.py
ppln/metrics/__init__.py
ppln/metrics/accuracy.py
ppln/schedulers/__init__.py
ppln/schedulers/warmup.py
ppln/utils/__init__.py
ppln/utils/checkpoint.py
ppln/utils/config.py
ppln/utils/log_buffer.py
ppln/utils/misc.py
ppln/utils/progress_bar.py
ppln/utils/registry.py
ppln/utils/timer.py
tests/__init__.py
tests/test_version.py