Metadata-Version: 2.1
Name: ppln
Version: 1.0.3
Summary: PyTorch runner
Home-page: https://github.com/ppln-team/ppln
Author: Miras Amir
Author-email: amirassov@gmail.com
License: UNKNOWN
Platform: UNKNOWN
Requires-Python: >=3.6.0
